tap_exchangeratehost/__init__.py
tap_exchangeratehost-0.1.2.dist-info/AUTHORS.md
tap_exchangeratehost-0.1.2.dist-info/LICENSE
tap_exchangeratehost-0.1.2.dist-info/METADATA
tap_exchangeratehost-0.1.2.dist-info/WHEEL
tap_exchangeratehost-0.1.2.dist-info/entry_points.txt
tap_exchangeratehost-0.1.2.dist-info/top_level.txt
tap_exchangeratehost-0.1.2.dist-info/RECORD
