Metadata-Version: 2.1
Name: tap-exchangeratehost
Version: 0.1.2
Summary: Singer.io tap for extracting currency exchange rate data from the exchangerate.host API
Home-page: http://github.com/anelendata/tap-exchangeratehost
Author: Daigo Tanaka, Anelen Co., LLC
Classifier: Development Status :: 4 - Beta
Classifier: License :: OSI Approved :: Apache Software License
Classifier: Operating System :: MacOS :: MacOS X
Classifier: Operating System :: POSIX :: Linux
Classifier: Programming Language :: Python :: 3.7
Classifier: Programming Language :: Python :: 3.8
Classifier: Programming Language :: Python :: 3.9
Classifier: Programming Language :: Python :: 3.10
Classifier: Programming Language :: Python :: 3.11
License-File: LICENSE
License-File: AUTHORS.md
Requires-Dist: singer-python (>=5.3.0)
Requires-Dist: requests (>=2.23.0)
